intellitext/__init__.py
intellitext/intellitext.py
intellitext-0.3.2.dist-info/licenses/LICENSE
intellitext-0.3.2.dist-info/METADATA
intellitext-0.3.2.dist-info/WHEEL
intellitext-0.3.2.dist-info/entry_points.txt
intellitext-0.3.2.dist-info/top_level.txt
intellitext-0.3.2.dist-info/RECORD
