Metadata-Version: 2.4
Name: intellitext
Version: 0.3.2
Summary: IntelliText is a powerful, customizable keyboard macro and text expansion tool that helps you automate repetitive typing tasks and execute custom actions. It's designed to boost your productivity by allowing you to create shortcuts for frequently used text, commands, and actions.
Author-email: Jack Scott <cloner.bl12@gmail.com>
Project-URL: Homepage, https://github.com/JackScott7/intellitext
Classifier: Development Status :: 3 - Alpha
Classifier: Intended Audience :: End Users/Desktop
Classifier: Topic :: Text Processing :: General
Classifier: License :: OSI Approved :: MIT License
Classifier: Programming Language :: Python :: 3
Classifier: Programming Language :: Python :: 3.13
Classifier: Operating System :: Microsoft :: Windows
Requires-Python: >=3.8
License-File: LICENSE
Requires-Dist: pyperclip>=1.8.2
Requires-Dist: pynput>=1.7.6
Dynamic: license-file
